zernikepy/__init__.py
zernikepy/plots.py
zernikepy/zernike_polynomials.py
ZernikePy-0.0.5.dist-info/LICENSE
ZernikePy-0.0.5.dist-info/METADATA
ZernikePy-0.0.5.dist-info/WHEEL
ZernikePy-0.0.5.dist-info/top_level.txt
ZernikePy-0.0.5.dist-info/RECORD
