Metadata-Version: 2.1
Name: ZernikePy
Version: 0.0.5
Summary: A minimalistic Python package to generate individual or a series of Zernike polynomials of arbitrary orders with visualization.
Author-email: Yan Liu <yanyan@ik.me>
Maintainer-email: Yan Liu <yanyan@ik.me>
Project-URL: Homepage, https://github.com/yanyan-liu/ZernikePy
Project-URL: Repository, https://github.com/yanyan-liu/ZernikePy
Project-URL: Issues, https://github.com/yanyan-liu/ZernikePy/issues
Keywords: zernike,psf,optics,polynomials,basis
Classifier: Programming Language :: Python :: 3
Classifier: License :: OSI Approved :: MIT License
Classifier: Operating System :: OS Independent
Requires-Python: >=3.8
License-File: LICENSE
Requires-Dist: numpy
Requires-Dist: scipy
Requires-Dist: matplotlib
